ragsys/__init__.py
ragsys/api_client.py
ragsys/api_response.py
ragsys/configuration.py
ragsys/exceptions.py
ragsys/py.typed
ragsys/rest.py
ragsys/api/__init__.py
ragsys/api/account_api.py
ragsys/api/completion_api.py
ragsys/api/database_api.py
ragsys/api/few_shot_example_api.py
ragsys/api/task_api.py
ragsys/models/__init__.py
ragsys/models/choice.py
ragsys/models/completion_body.py
ragsys/models/completion_response.py
ragsys/models/content.py
ragsys/models/content_item.py
ragsys/models/content_item_type.py
ragsys/models/create_database_request.py
ragsys/models/create_or_partial_update_examples_response.py
ragsys/models/custom_validation_error.py
ragsys/models/database_item.py
ragsys/models/database_list_response.py
ragsys/models/detail.py
ragsys/models/error_response.py
ragsys/models/example.py
ragsys/models/example_response.py
ragsys/models/examples_body.py
ragsys/models/examples_response.py
ragsys/models/get_configuration_response.py
ragsys/models/http_validation_error.py
ragsys/models/image_url.py
ragsys/models/init_database_response.py
ragsys/models/llm_list_models_response.py
ragsys/models/login_request.py
ragsys/models/login_response.py
ragsys/models/message_completion_content.py
ragsys/models/message_content.py
ragsys/models/message_role.py
ragsys/models/reset_password.py
ragsys/models/reset_password_response.py
ragsys/models/retrieval.py
ragsys/models/retrieve_examples.py
ragsys/models/retrieve_examples_response.py
ragsys/models/send_reset_password_request.py
ragsys/models/task_response.py
ragsys/models/task_status.py
ragsys/models/task_type.py
ragsys/models/task_with_details_response.py
ragsys/models/update_database.py
ragsys/models/usage.py
ragsys/models/validation_error.py
ragsys/models/validation_error_detail.py
ragsys/models/validation_error_detail_loc_inner.py
ragsys/models/validation_error_loc_inner.py
ragsys-1.0.1.dist-info/METADATA
ragsys-1.0.1.dist-info/WHEEL
ragsys-1.0.1.dist-info/top_level.txt
ragsys-1.0.1.dist-info/RECORD
