Metadata-Version: 2.4
Name: ragsys
Version: 1.0.1
Summary: Crossing Minds RAGsys python library
Home-page: 
Author: Crossing Minds
Author-email: contact@crossingminds.com
Keywords: Crossing Minds,CM,RAGsys,ai,openai,RAGsys API
Requires-Python: >= 3.8
Requires-Dist: urllib3<3.0.0,>=1.25.3
Requires-Dist: python-dateutil>=2.8.2
Requires-Dist: pydantic>=2
Requires-Dist: typing-extensions>=4.7.1
Dynamic: author
Dynamic: author-email
Dynamic: description
Dynamic: description-content-type
Dynamic: keywords
Dynamic: requires-dist
Dynamic: requires-python
Dynamic: summary
